passwordless_login/__init__.py
passwordless_login/apps.py
passwordless_login/settings.py
passwordless_login/tests.py
passwordless_login/urls.py
passwordless_login/views.py
passwordless_login/migrations/__init__.py
passwordless_login/templates/passwordless_login/login.html
django_passwordless_login-0.0.3.dist-info/LICENSE
django_passwordless_login-0.0.3.dist-info/METADATA
django_passwordless_login-0.0.3.dist-info/WHEEL
django_passwordless_login-0.0.3.dist-info/top_level.txt
django_passwordless_login-0.0.3.dist-info/RECORD
