Metadata-Version: 2.1
Name: django-passwordless-login
Version: 0.0.3
Summary: Login to your Django app with a link sent by email.
Home-page: https://github.com/ImperialCollegeLondon/django-passwordless-login
Author: Adrian D'Alessandro
Author-email: a.dalessandro@imperial.ac.uk
License: BSD-3-Clause
Classifier: Development Status :: 3 - Alpha
Classifier: Intended Audience :: Developers
Classifier: Programming Language :: Python :: 3.8
Classifier: Programming Language :: Python :: 3.9
License-File: LICENSE
Requires-Dist: Django
Requires-Dist: django-sesame[ua]
